safire/__init__.py
safire/config.py
safire/creds/.gitignore
safire/creds/.keep
safire/data/.gitignore
safire/data/.keep
safire/default_config.py
safire/safire.py
safire/safire_ip.py
safire/setup.exe
safire/svcaccts/.gitignore
safire/svcaccts/.keep
safire/utils.py
safire-0.2.6.dist-info/entry_points.txt
safire-0.2.6.dist-info/WHEEL
safire-0.2.6.dist-info/METADATA
safire-0.2.6.dist-info/RECORD
