Metadata-Version: 2.1
Name: safire
Version: 0.2.6
Summary: A flexible tool to create and delete Google / GSuite service accounts to be used with shared drives.
Keywords: gsuite,sas,service accounts
Author: 88lex
Requires-Python: >=3.6.1,<4.0.0
Classifier: Programming Language :: Python :: 3
Classifier: Programming Language :: Python :: 3.7
Classifier: Programming Language :: Python :: 3.8
Classifier: Programming Language :: Python :: 3.9
Requires-Dist: fire (>=0.3.1,<0.4.0)
Requires-Dist: google-api-python-client (>=1.10.0,<2.0.0)
Requires-Dist: google-auth-oauthlib (>=0.4.1,<0.5.0)
Requires-Dist: oauth2client (>=4.1.3,<5.0.0)
Requires-Dist: openpyxl (>=3.0.4,<4.0.0)
Requires-Dist: pandas (>=1.0.5,<2.0.0)
Requires-Dist: requests (>=2.24.0,<3.0.0)
Requires-Dist: uuid (>=1.30,<2.0)
